uw_catalyst/VERSION
uw_catalyst/__init__.py
uw_catalyst/dao.py
uw_catalyst/exceptions.py
uw_catalyst/gradebook.py
uw_catalyst/models.py
uw_catalyst/survey.py
uw_catalyst/test.py
uw_catalyst/util.py
uw_catalyst/resources/catalyst/file/rest/gradebook/v1/book/12345/participants
uw_catalyst/resources/catalyst/file/rest/gradebook/v1/section/2013_summer_CSS_161/A/participants
uw_catalyst/tests/__init__.py
uw_catalyst/tests/test_dao.py
uw_catalyst/tests/test_gradebook.py
uw_catalyst/tests/test_survey.py
UW_RestClients_Catalyst-1.1.2.dist-info/LICENSE
UW_RestClients_Catalyst-1.1.2.dist-info/METADATA
UW_RestClients_Catalyst-1.1.2.dist-info/WHEEL
UW_RestClients_Catalyst-1.1.2.dist-info/top_level.txt
UW_RestClients_Catalyst-1.1.2.dist-info/RECORD
