Metadata-Version: 2.1
Name: UW-RestClients-Catalyst
Version: 1.1.2
Summary: A library for connecting to the UW Catalyst REST API
Home-page: https://github.com/uw-it-aca/uw-restclients-catalyst
Author: UW-IT AXDD
Author-email: aca-it@uw.edu
License: Apache License, Version 2.0
Platform: UNKNOWN
Classifier: Intended Audience :: Developers
Classifier: License :: OSI Approved :: Apache Software License
Classifier: Operating System :: OS Independent
Classifier: Programming Language :: Python
Classifier: Programming Language :: Python :: 3.6
License-File: LICENSE
Requires-Dist: UW-RestClients-Core
Requires-Dist: UW-RestClients-SWS (~=2.3)
Requires-Dist: UW-RestClients-PWS (~=2.1)
Requires-Dist: mock
